<Properties StartupConfiguration="{576EE1FE-C7B6-4A15-854A-6E3B3D7C805C}|Default">
  <MonoDevelop.Ide.ItemProperties.ImagePicker HideGettingStarted="True" />
  <MonoDevelop.Ide.Workbench ActiveDocument="iOS/ImagePicker/ViewControllers/ImagePickerViewController.cs">
    <Files>
      <File FileName="iOS/ImagePicker/ViewControllers/ImagePickerViewController.cs" Line="80" Column="51" />
      <File FileName="iOS/ImagePicker/Models/ImagePickerSection.cs" Line="14" Column="36" />
      <File FileName="iOS/Main.cs" Line="17" Column="1" />
      <File FileName="iOS/ImagePicker/Cells/TakePhotoCollectionViewCell.cs" Line="26" Column="51" />
      <File FileName="iOS/ImagePicker/Cells/SelectableImageCollectionViewCell.cs" Line="54" Column="68" />
    </Files>
  </MonoDevelop.Ide.Workbench>
  <MonoDevelop.Ide.Workspace ActiveConfiguration="Debug" />
  <MonoDevelop.Ide.DebuggingService.Breakpoints>
    <BreakpointStore />
  </MonoDevelop.Ide.DebuggingService.Breakpoints>
  <MonoDevelop.Ide.DebuggingService.PinnedWatches />
  <MonoDevelop.Ide.ItemProperties.ImagePicker.iOS PreferredExecutionTarget="MonoDevelop.IPhone.IPhoneSimulatorTarget.1876EEAC-6876-46F7-B881-9D2A929D37EB" />
  <MultiItemStartupConfigurations />
  <MonoDevelop.Ide.ItemProperties.ImagePicker.Droid FirstBuild="True" />
</Properties>